zeroeventhub/__init__.py
zeroeventhub/api_handler.py
zeroeventhub/client.py
zeroeventhub/constants.py
zeroeventhub/cursor.py
zeroeventhub/data_reader.py
zeroeventhub/errors.py
zeroeventhub/event.py
zeroeventhub/event_receiver.py
zeroeventhub/page_event_receiver.py
zeroeventhub/py.typed
zeroeventhub/response_line_iterator.py
zeroeventhub-0.2.4.dist-info/METADATA
zeroeventhub-0.2.4.dist-info/WHEEL
zeroeventhub-0.2.4.dist-info/RECORD
