Metadata-Version: 2.1
Name: zeroeventhub
Version: 0.2.4
Summary: Broker-less event streaming over HTTP
Home-page: https://github.com/vippsas/zeroeventhub
License: MIT
Keywords: event-streaming
Author: Vipps MobilePay
Requires-Python: >=3.13,<4.0
Classifier: License :: OSI Approved :: MIT License
Classifier: Programming Language :: Python :: 3
Classifier: Programming Language :: Python :: 3.13
Requires-Dist: fastapi (>=0.115,<0.116)
Requires-Dist: httpx (>=0.27,<0.28)
Project-URL: Repository, https://github.com/vippsas/zeroeventhub
